cartotools/__init__.py
cartotools/crs/__init__.py
cartotools/crs/epsg2056.py
cartotools/crs/epsg2154.py
cartotools/crs/epsg28992.py
cartotools/crs/epsg3112.py
cartotools/crs/epsg3348.py
cartotools/crs/epsg5680.py
cartotools/crs/epsg6350.py
cartotools/crs/epsg9221.py
cartotools/img_tiles/__init__.py
cartotools/img_tiles/arcgis.py
cartotools/img_tiles/bkg.py
cartotools/img_tiles/brt.py
cartotools/img_tiles/cached.py
cartotools/img_tiles/ign.py
cartotools/img_tiles/ngi.py
cartotools/img_tiles/oaci.py
cartotools/img_tiles/openflights.py
cartotools/osm/__init__.py
cartotools/osm/core.py
cartotools/osm/nominatim.py
cartotools/osm/overpass.py
cartotools/osm/tags.py
cartotools/osm/tags_extra.py
cartotools/osm/tools.py
cartotools-1.2.2.dist-info/METADATA
cartotools-1.2.2.dist-info/WHEEL
cartotools-1.2.2.dist-info/top_level.txt
cartotools-1.2.2.dist-info/RECORD
