Metadata-Version: 2.1
Name: cartotools
Version: 1.2.2
Summary: Making cartopy suit my needs
Home-page: UNKNOWN
Author: Xavier Olive
Author-email: UNKNOWN
License: MIT
Platform: UNKNOWN
Requires-Dist: pandas
